{"jVhiNw2qew2SvQIbqm2xUw==":"renda%20extra%20em%20d%C3%B3lar%20-%20post%20para%20feed%20de%20instagram%20(instagram%20post)%20(5)-1080x1080.png","HtZ0gLEtqqRIZuW/kVmjVg==":"renda%20extra%20em%20d%C3%B3lar%20-%20post%20para%20feed%20de%20instagram%20(instagram%20post)%20(5)-1080x1080.png","78op09W/blgybLbIfztonw==":"renda%20extra%20em%20d%C3%B3lar%20-%20post%20para%20feed%20de%20instagram%20(instagram%20post)%20(5)-1080x1080.png","qMOJu0hBpHqWQj3Df4N+0w==":"atacado%20nt%20(1)-1080x1080.png","oZR0CiZUNx+cs2lmEqa0bw==":"renda%20extra%20em%20d%C3%B3lar%20-%20post%20para%20feed%20de%20instagram%20(instagram%20post)%20(2)-1080x1080.png","dG9kgl838FyTLVOV0ABhLA==":"renda%20extra%20em%20d%C3%B3lar%20-%20post%20para%20feed%20de%20instagram%20(instagram%20post)%20(1)-1080x1080.png","OFluuw1xygS4tYrJQXnSeA==":"renda%20extra%20em%20d%C3%B3lar%20-%20post%20para%20feed%20de%20instagram%20(instagram%20post)%20(6)-1080x1080.png","Bwlm6hiYseVCYXCwksUU1Q==":"renda%20extra%20em%20d%C3%B3lar%20-%20post%20para%20feed%20de%20instagram%20(instagram%20post)-1080x1080.png","lIMjHMJLEL3NROOp3B9QKA==":"renda%20extra%20em%20d%C3%B3lar%20-%20post%20para%20feed%20de%20instagram%20(instagram%20post)%20(7)-1080x1080.png","pcVhBlcrG714n5wqddrzbA==":"renda%20extra%20em%20d%C3%B3lar%20-%20post%20para%20feed%20de%20instagram%20(instagram%20post)%20(8)-816x816.png","AbvxSRzg4y2nVpGFUExI3g==":"orange%20e-commerce%20online%20store%20logo%20(3)-816x816.png","yp0CXJPhK/mTTAswYNefeg==":"renda%20extra%20em%20d%C3%B3lar%20-%20post%20para%20feed%20de%20instagram%20(instagram%20post)%20(5)-1080x1080.png","z1s4m4ZNTYBJVW7GvGzinQ==":"orange%20e-commerce%20online%20store%20logo-121x121.png","eS5HBtb/NxB5djT061rfPw==":"renda%20extra%20em%20d%C3%B3lar%20-%20post%20para%20feed%20de%20instagram%20(instagram%20post)%20(5)-1080x1080.png","oKmDIkFBx3m/8O5lE4HQbw==":"orange%20e-commerce%20online%20store%20logo-1080x1080.png","CRHFZmNpjiynZvpvASQTWA==":"orange%20e-commerce%20online%20store%20logo-1080x1080.png","wxRgEX3UmND91YrVAYTTMA==":"orange%20e-commerce%20online%20store%20logo-1080x1080.png","zleZdac0sg053Wa7Umneng==":"mbr-1920x1280.jpg","0eEEcwAKiF1SJAV6G8IOfA==":"renda%20extra%20em%20d%C3%B3lar%20-%20post%20para%20feed%20de%20instagram%20(instagram%20post)%20(3)-1080x1080.png"}